awslabs/__init__.py
awslabs/dynamodb_mcp_server/__init__.py
awslabs/dynamodb_mcp_server/common.py
awslabs/dynamodb_mcp_server/markdown_formatter.py
awslabs/dynamodb_mcp_server/model_validation_utils.py
awslabs/dynamodb_mcp_server/server.py
awslabs/dynamodb_mcp_server/cdk_generator/__init__.py
awslabs/dynamodb_mcp_server/cdk_generator/generator.py
awslabs/dynamodb_mcp_server/cdk_generator/models.py
awslabs/dynamodb_mcp_server/cdk_generator/templates/README.md
awslabs/dynamodb_mcp_server/cdk_generator/templates/stack.ts.j2
awslabs/dynamodb_mcp_server/db_analyzer/__init__.py
awslabs/dynamodb_mcp_server/db_analyzer/analyzer_utils.py
awslabs/dynamodb_mcp_server/db_analyzer/base_plugin.py
awslabs/dynamodb_mcp_server/db_analyzer/mysql.py
awslabs/dynamodb_mcp_server/db_analyzer/plugin_registry.py
awslabs/dynamodb_mcp_server/db_analyzer/postgresql.py
awslabs/dynamodb_mcp_server/db_analyzer/sqlserver.py
awslabs/dynamodb_mcp_server/prompts/dynamodb_architect.md
awslabs/dynamodb_mcp_server/prompts/json_generation_guide.md
awslabs/dynamodb_mcp_server/prompts/transform_model_validation_result.md
awslabs_dynamodb_mcp_server-2.0.12.dist-info/METADATA
awslabs_dynamodb_mcp_server-2.0.12.dist-info/WHEEL
awslabs_dynamodb_mcp_server-2.0.12.dist-info/entry_points.txt
awslabs_dynamodb_mcp_server-2.0.12.dist-info/licenses/LICENSE
awslabs_dynamodb_mcp_server-2.0.12.dist-info/licenses/NOTICE
awslabs_dynamodb_mcp_server-2.0.12.dist-info/RECORD
