Metadata-Version: 2.4
Name: awslabs.dynamodb-mcp-server
Version: 2.0.12
Summary: The official MCP Server for interacting with AWS DynamoDB
Project-URL: homepage, https://awslabs.github.io/mcp/
Project-URL: docs, https://awslabs.github.io/mcp/servers/dynamodb-mcp-server/
Project-URL: documentation, https://awslabs.github.io/mcp/servers/dynamodb-mcp-server/
Project-URL: repository, https://github.com/awslabs/mcp.git
Project-URL: changelog, https://github.com/awslabs/mcp/blob/main/src/dynamodb-mcp-server/CHANGELOG.md
Author: Amazon Web Services
Author-email: AWSLabs MCP <203918161+awslabs-mcp@users.noreply.github.com>, Erben Mo <moerben@amazon.com>
License: Apache-2.0
License-File: LICENSE
License-File: NOTICE
Classifier: License :: OSI Approved :: Apache Software License
Classifier: Operating System :: OS Independent
Classifier: Programming Language :: Python
Classifier: Programming Language :: Python :: 3
Classifier: Programming Language :: Python :: 3.10
Classifier: Programming Language :: Python :: 3.11
Classifier: Programming Language :: Python :: 3.12
Classifier: Programming Language :: Python :: 3.13
Requires-Python: >=3.10
Requires-Dist: awslabs-aws-api-mcp-server==1.0.2
Requires-Dist: awslabs-mysql-mcp-server==1.0.9
Requires-Dist: boto3>=1.40.5
Requires-Dist: dspy-ai>=2.6.27
Requires-Dist: jinja2>=3.1.0
Requires-Dist: loguru==0.7.3
Requires-Dist: mcp[cli]==1.23.0
Requires-Dist: psutil==7.1.1
Requires-Dist: pydantic==2.11.7
Requires-Dist: strands-agents>=1.5.0
Requires-Dist: typing-extensions==4.14.1
